quickpanda/__init__.py
quickpanda/analysis.py
quickpanda/file_operate.py
quickpanda/hyper.py
quickpanda/modeling.py
quickpanda/ploting.py
quickpanda/preprocess.py
quickpanda/statistic_test.py
quickpanda/utils.py
quickpanda-0.0.5.dist-info/METADATA
quickpanda-0.0.5.dist-info/WHEEL
quickpanda-0.0.5.dist-info/top_level.txt
quickpanda-0.0.5.dist-info/RECORD
