Metadata-Version: 2.1
Name: quickpanda
Version: 0.0.5
Summary: quickpanda
Home-page: https://github.com/yasuo626/QuickPanda
Author: aidroid
Author-email: yasuo626.com@gmail.com
Keywords: data analysis
Classifier: Programming Language :: Python :: 3
Classifier: License :: OSI Approved :: MIT License
Classifier: Operating System :: OS Independent
Requires-Python: >=3.6
